setup.py
snp/__init__.py
snp.egg-info/PKG-INFO
snp.egg-info/SOURCES.txt
snp.egg-info/dependency_links.txt
snp.egg-info/top_level.txt