Metadata-Version: 1.0
Name: snp
Version: 0.0.1
Summary: freeze inputs and outputs to functions for refactoring
Home-page: https://github.com/frnsys/snp
Author: Francis Tseng (@frnsys)
Author-email: UNKNOWN
License: MIT
Platform: UNKNOWN
